Metadata-Version: 1.1
Name: Resea
Version: 0.2
Summary: A Resea developer kit
Home-page: http://resea.net
Author: Seiya Nuta
Author-email: nuta@seiya.me
License: Public Domain
Platform: UNKNOWN
Classifier: Development Status :: 2 - Pre-Alpha
Classifier: Intended Audience :: Developers
Classifier: License :: Public Domain
Classifier: Programming Language :: Python :: 3
